huaweicloudsdkmssi/__init__.py
huaweicloudsdkmssi/v1/__init__.py
huaweicloudsdkmssi/v1/mssi_async_client.py
huaweicloudsdkmssi/v1/mssi_client.py
huaweicloudsdkmssi/v1/model/__init__.py
huaweicloudsdkmssi/v1/model/action_base_info.py
huaweicloudsdkmssi/v1/model/api_config.py
huaweicloudsdkmssi/v1/model/auth_config_a.py
huaweicloudsdkmssi/v1/model/base_connection_info.py
huaweicloudsdkmssi/v1/model/connection_info.py
huaweicloudsdkmssi/v1/model/connector_info.py
huaweicloudsdkmssi/v1/model/connector_info0.py
huaweicloudsdkmssi/v1/model/create_connection_info_request.py
huaweicloudsdkmssi/v1/model/create_connection_info_response.py
huaweicloudsdkmssi/v1/model/create_custom_connector_from_openapi_request.py
huaweicloudsdkmssi/v1/model/create_custom_connector_from_openapi_response.py
huaweicloudsdkmssi/v1/model/create_flow_request.py
huaweicloudsdkmssi/v1/model/create_flow_response.py
huaweicloudsdkmssi/v1/model/create_flow_template_from_flow_request.py
huaweicloudsdkmssi/v1/model/create_flow_template_from_flow_response.py
huaweicloudsdkmssi/v1/model/custom_connector_info_v2.py
huaweicloudsdkmssi/v1/model/delete_connection_info_request.py
huaweicloudsdkmssi/v1/model/delete_connection_info_response.py
huaweicloudsdkmssi/v1/model/delete_custom_connector_request.py
huaweicloudsdkmssi/v1/model/delete_custom_connector_response.py
huaweicloudsdkmssi/v1/model/delete_flow_request.py
huaweicloudsdkmssi/v1/model/delete_flow_response.py
huaweicloudsdkmssi/v1/model/flow_meta.py
huaweicloudsdkmssi/v1/model/runtime_permission.py
huaweicloudsdkmssi/v1/model/search_flow_by_id_request.py
huaweicloudsdkmssi/v1/model/search_flow_by_id_response.py
huaweicloudsdkmssi/v1/model/show_all_connections_request.py
huaweicloudsdkmssi/v1/model/show_all_connections_response.py
huaweicloudsdkmssi/v1/model/show_all_flows_request.py
huaweicloudsdkmssi/v1/model/show_all_flows_response.py
huaweicloudsdkmssi/v1/model/show_connectors_request.py
huaweicloudsdkmssi/v1/model/show_connectors_response.py
huaweicloudsdkmssi-3.1.184.dist-info/METADATA
huaweicloudsdkmssi-3.1.184.dist-info/WHEEL
huaweicloudsdkmssi-3.1.184.dist-info/licenses/LICENSE
huaweicloudsdkmssi-3.1.184.dist-info/RECORD
